{
  "name": "Xcode Dracula Theme",
  "type": "dark",
  "colors": {
    // Activity Bar
    "activityBar.background": "#2a2c2f",
    "activityBar.border": "#000000",
    "activityBar.foreground": "#dfdfdf",
    "activityBarBadge.background": "#FFC799",
    "activityBarBadge.foreground": "#000000",
    // Breadcrumb
    "breadcrumb.background": "#1c1f21",
    "breadcrumb.focusForeground": "#dcdddd",
    "breadcrumb.foreground": "#dcdddd",
    // Debug
    "debugIcon.breakpointCurrentStackframeForeground": "#007aff22",
    "debugIcon.breakpointForeground": "#007aff22",
    // Diff Editor
    "diffEditor.insertedTextBackground": "#3cff5518",
    "diffEditor.removedTextBackground": "#ff504418",
    // Editor
    "editor.background": "#1F1F24",
    "editor.foreground": "#FFFFFF",
    "editor.lineHighlightBackground": "#292A2F",
    "editor.selectionBackground": "#1757BE33",
    "editor.hoverHighlightBackground": "#2c5392",
    "editor.findMatchBackground": "#F1FA8C",
    "editor.findMatchHighlightBackground": "#545558",
    "editor.snippetTabstopHighlightBackground": "#007aff22",
    "editor.stackFrameHighlightBackground": "#007aff22",
    "editorCodeLens.foreground": "#dfdfdf77",
    "editorCursor.foreground": "#ffffff",
    "editorError.foreground": "#FF5555",
    "editorGroupHeader.noTabsBackground": "#383a3d",
    "editorGroupHeader.tabsBackground": "#26282b",
    "editorGutter.addedBackground": "#50FA7B",
    "editorGutter.deletedBackground": "#FF5555",
    "editorGutter.modifiedBackground": "#BD93F9",
    "editorIndentGuide.activeBackground": "#00000000",
    "editorIndentGuide.background": "#00000000",
    "editorLineNumber.activeForeground": "#FFFFFF",
    "editorLineNumber.foreground": "#FFFFFF55",
    "editorLink.activeForeground": "#6699ff",
    "editorOverviewRuler.addedForeground": "#50FA7B",
    "editorOverviewRuler.deletedForeground": "#FF5555",
    "editorOverviewRuler.errorForeground": "#FF5555",
    "editorOverviewRuler.findMatchForeground": "#F1FA8C",
    "editorOverviewRuler.modifiedForeground": "#BD93F9",
    "editorOverviewRuler.warningForeground": "#f5c443",
    "editorWarning.foreground": "#f5c443",
    "editorWhitespace.foreground": "#646E83",
    "editorWidget.background": "#303030",
    // Editor Inlay Hint
    "editorInlayHint.foreground": "#A0A0A0",
    "editorInlayHint.background": "#1C1C1C",
    // Errors and Warnings
    "errorForeground": "#FF5555",
    "focusBorder": "#335274",
    // General Foreground
    "foreground": "#F8F8F2",
    // Git Decorations
    "gitDecoration.conflictingResourceForeground": "#FF5555",
    "gitDecoration.ignoredResourceForeground": "#dfdfdf55",
    // List
    "list.activeSelectionBackground": "#3F4F74",
    "list.activeSelectionForeground": "#dfdfdf",
    "list.focusBackground": "#6272A4",
    "list.focusForeground": "#dfdfdf",
    "list.highlightForeground": "#f5c443",
    "list.hoverBackground": "#00000000",
    "list.inactiveSelectionBackground": "#4f5153",
    "list.errorForeground": "#FF5555",
    // Minimap
    "minimap.errorHighlight": "#FF5555",
    "minimap.findMatchHighlight": "#F1FA8C",
    "minimap.selectionHighlight": "#646f83",
    "minimap.warningHighlight": "#f5c443",
    "minimapGutter.addedBackground": "#50FA7B",
    "minimapGutter.deletedBackground": "#FF5555",
    "minimapGutter.modifiedBackground": "#BD93F9",
    // Panel
    "panel.border": "#000000",
    // Peek View
    "peekView.border": "#6272A4",
    "peekViewEditor.background": "#292a30",
    "peekViewEditor.matchHighlightBackground": "#545558",
    "peekViewResult.background": "#2a2c2f",
    "peekViewResult.fileForeground": "#dfdfdf",
    "peekViewResult.lineForeground": "#dfdfdf99",
    "peekViewResult.matchHighlightBackground": "#545558",
    "peekViewResult.selectionBackground": "#6272A4",
    "peekViewResult.selectionForeground": "#dfdfdf",
    "peekViewTitle.background": "#2a2c2f",
    "peekViewTitleDescription.foreground": "#6699ff",
    "peekViewTitleLabel.foreground": "#dfdfdf",
    // Search Editor
    "searchEditor.findMatchBackground": "#F1FA8C",
    // Sidebar
    "sideBar.background": "#222223",
    "sideBar.border": "#000000",
    "sideBarSectionHeader.background": "#00000000",
    "sideBarSectionHeader.foreground": "#dfdfdf",
    "sideBarTitle.foreground": "#dfdfdf",
    // Status Bar
    "statusBar.background": "#202020",
    "statusBar.border": "#000000",
    "statusBar.debuggingBackground": "#202020",
    "statusBar.debuggingBorder": "#000000",
    "statusBar.debuggingForeground": "#FFF",
    "statusBar.foreground": "#FFF",
    "statusBar.noFolderBackground": "#202020",
    "statusBar.noFolderBorder": "#000000",
    "statusBar.noFolderForeground": "#FFF",
    // Tabs
    "tab.activeBackground": "#292929",
    "tab.activeForeground": "#ffffff",
    "tab.border": "#26282b",
    "tab.inactiveBackground": "#26282b",
    "tab.inactiveForeground": "#9a9c9d",
    "tab.activeBorder": "#FFC799",
    // Text Link
    "textLink.activeForeground": "#6699ff",
    "textLink.foreground": "#6699ff",
    // Title Bar
    "titleBar.activeBackground": "#21222C",
    "titleBar.activeForeground": "#F8F8F2",
    "titleBar.border": "#26282b",
    "titleBar.inactiveBackground": "#191A21",
    "titleBar.inactiveForeground": "#6272A4",
    // Meta
    "meta.type.annotation": "#D0A8FF",
    // Badge
    "badge.background": "#FFC799",
    "badge.foreground": "#000",
    // Button
    "button.background": "#FFC799",
    "button.hoverBackground": "#FFCFA8",
    "button.foreground": "#000",
    // Scrollbar
    "scrollbarSlider.background": "#44444580",
    "scrollbarSlider.hoverBackground": "#444445",
    // Settings
    "settings.modifiedItemIndicator": "#FFC799",
    // Icons and Inputs
    "icon.foreground": "#dfdfdf",
    "input.background": "#1c1f21",
    // Global selection (outside the editor)
    "selection.background": "#646f83",
    // Bracket Pair Colorization
    "editorBracketHighlight.foreground1": "#8BE9FD",
    "editorBracketHighlight.foreground2": "#50FA7B",
    "editorBracketHighlight.foreground3": "#FF79C6",
    "editorBracketHighlight.foreground4": "#BD93F9",
    "editorBracketHighlight.foreground5": "#F1FA8C",
    "editorBracketHighlight.foreground6": "#FFB86C",
    "editorBracketHighlight.unexpectedBracket.foreground": "#FF5555",
    // Hover Widget
    "editorHoverWidget.background": "#444445",
    "editorHoverWidget.border": "#373737"
  },
  "tokenColors": [
    {
      "scope": [
        "comment",
        "punctuation.definition.comment"
      ],
      "settings": {
        "foreground": "#6272A4"
      }
    },
    {
      "scope": [
        "punctuation.definition.string",
        "string"
      ],
      "settings": {
        "foreground": "#FF79C6"
      }
    },
    {
      "scope": [
        "constant.numeric",
        "keyword.other.unit",
        "support.constant"
      ],
      "settings": {
        "foreground": "#F1FA8C"
      }
    },
    {
      "scope": [
        "constant.language",
        "entity.name.tag",
        "keyword",
        "storage.modifier",
        "storage.type",
        "support.type.primitive",
        "variable.language"
      ],
      "settings": {
        "foreground": "#FF79C6",
        "fontStyle": "bold"
      }
    },
    {
      "scope": [
        "keyword.control.directive",
        "keyword.control.preprocessor",
        "punctuation.definition.preprocessor"
      ],
      "settings": {
        "foreground": "#FFB86C"
      }
    },
    {
      "scope": [
        "markup.underline.link"
      ],
      "settings": {
        "foreground": "#8BE9FD"
      }
    },
    {
      "scope": [
        "entity.name.type.class.std.rust",
        "storage.type.cs",
        "support.type",
        "meta.object-literal.key"
      ],
      "settings": {
        "foreground": "#BD93F9"
      }
    },
    {
      "scope": [
        "meta.object-literal.key"
      ],
      "settings": {
        "foreground": "#BD93F9"
      }
    },
    {
      "scope": [
        "punctuation.definition.variable",
        "punctuation.support.type.property-name",
        "storage.modifier.lifetime",
        "support.type.property-name",
        "variable.other.property"
      ],
      "settings": {
        "foreground": "#83C9BC"
      }
    },
    {
      "scope": [
        "meta.definition.function",
        "meta.definition.method",
        "meta.method.declaration"
      ],
      "settings": {
        "foreground": "#8BE9FD"
      }
    },
    {
      "scope": [
        "variable.other.constant",
        "meta.definition.variable"
      ],
      "settings": {
        "foreground": "#FFFFFF"
      }
    },
    {
      "scope": [
        "variable.parameter",
        "meta.parameters",
        "meta.method.declaration",
        "meta.object.member"
      ],
      "settings": {
        "foreground": "#48b7db"
      }
    },
    {
      "scope": [
        "variable.other.object",
        "meta.var.expr",
        "meta.definition.variable",
        "meta.block"
      ],
      "settings": {
        "foreground": "#48b7db"
      }
    },
    {
      "scope": [
        "constant.language.boolean.false",
        "constant.language.boolean.true",
        "meta.objectliteral"
      ],
      "settings": {
        "foreground": "#F1FA8C"
      }
    },
    {
      "scope": [
        "entity.name.type"
      ],
      "settings": {
        "foreground": "#BD93F9"
      }
    },
    {
      "scope": [
        "entity.name.type.class",
        "entity.other.inherited-class"
      ],
      "settings": {
        "foreground": "#8BE9FD"
      }
    },
    {
      "scope": [
        "keyword.operator"
      ],
      "settings": {
        "foreground": "#FF79C6"
      }
    },
    {
      "scope": [
        "meta.return.type",
        "meta.function",
        "support.type.primitive",
        "meta.field.declaration",
        "meta.interface"
      ],
      "settings": {
        "foreground": "#BD93F9"
      }
    },
    {
      "scope": [
        "meta.function-call"
      ],
      "settings": {
        "foreground": "#CDA1FF"
      }
    },
    {
      "scope": [
        "entity.name.type.namespace",
        "entity.name.variable",
        "variable.other.assignment"
      ],
      "settings": {
        "foreground": "#49B7D7"
      }
    },
    {
      "scope": [
        "variable.object.property",
        "meta.definition.property",
        "meta.field.declaration",
        "meta.class"
      ],
      "settings": {
        "foreground": "#49B7D7"
      }
    },
    {
      "scope": [
        "fenced_code.block.language",
        "punctuation.definition.bold.markdown",
        "punctuation.definition.heading.markdown",
        "punctuation.definition.italic.markdown",
        "punctuation.definition.list.begin.markdown",
        "punctuation.definition.markdown",
        "punctuation.definition.metadata.markdown",
        "punctuation.definition.quote.begin.markdown",
        "punctuation.definition.raw.markdown",
        "punctuation.definition.string.begin.markdown",
        "punctuation.definition.string.end.markdown"
      ],
      "settings": {
        "foreground": "#72BFAE"
      }
    },
    {
      "scope": [
        "string.other.link.title.markdown"
      ],
      "settings": {
        "foreground": "#DFDFE0"
      }
    },
    {
      "scope": [
        "entity.name.section"
      ],
      "settings": {
        "foreground": "#DFDFE0",
        "fontStyle": "bold"
      }
    },
    {
      "scope": [
        "variable.other.object.property",
        "support.variable.property",
        "variable.other.constant.property"
      ],
      "settings": {
        "foreground": "#83C9BC"
      }
    },
    {
      "scope": [
        "markup.bold"
      ],
      "settings": {
        "foreground": "#DFDFE0",
        "fontStyle": "bold"
      }
    },
    {
      "scope": [
        "markup.italic"
      ],
      "settings": {
        "foreground": "#DFDFE0",
        "fontStyle": "italic"
      }
    },
    {
      "scope": [
        "punctuation"
      ],
      "settings": {
        "foreground": "#DFDFE0"
      }
    },
    {
      "scope": [
        "punctuation.decorator",
        "meta.brace.round"
      ],
      "settings": {
        "foreground": "#FFFFFF"
      }
    },
    {
      "scope": [
        "entity.other.attribute-name"
      ],
      "settings": {
        "foreground": "#BD93F9"
      }
    },
    {
      "scope": [
        "meta.tag.without-attributes",
        "metax.children"
      ],
      "settings": {
        "foreground": "#FFFFFF"
      }
    },
    {
      "scope": [
        "variable.other.readwrite.alias"
      ],
      "settings": {
        "foreground": "#FFFFFF"
      }
    },
    {
      "scope": [
        "punctuation.terminator.statement"
      ],
      "settings": {
        "foreground": "#FFFFFF"
      }
    },
    {
      "scope": [
        "punctuation.accessor.optional"
      ],
      "settings": {
        "foreground": "#FF79C6"
      }
    },
    {
      "scope": [
        "case-clause.expr",
        "switch-block.expr",
        "switch-statement.expr"
      ],
      "settings": {
        "foreground": "#48b7db"
      }
    },
    {
      "scope": "token.info-token",
      "settings": {
        "foreground": "#6796E6"
      }
    },
    {
      "scope": "token.warn-token",
      "settings": {
        "foreground": "#CD9731"
      }
    },
    {
      "scope": "token.error-token",
      "settings": {
        "foreground": "#F44747"
      }
    },
    {
      "scope": "token.debug-token",
      "settings": {
        "foreground": "#B267E6"
      }
    },
    {
      "scope": [
        "support.class.dart",
        "other.source.dart"
      ],
      "settings": {
        "foreground": "#BD93F9"
      }
    },
    {
      "scope": [
        "entity.name.function.dart"
      ],
      "settings": {
        "foreground": "#8BE9FD"
      }
    },
    {
      "scope": [
        "source.dart"
      ],
      "settings": {
        "foreground": "#49B7D7"
      }
    },
    {
      "scope": [
        "variable.parameter.dart"
      ],
      "settings": {
        "foreground": "#83C9BC"
      }
    },
    // JSON Keys (Level 0 to 8)
    {
      "name": "JSON Key - Level 0",
      "scope": [
        "source.json meta.structure.dictionary.json support.type.property-name.json"
      ],
      "settings": {
        "foreground": "#BD93F9"
      }
    },
    {
      "name": "JSON Key - Level 1",
      "scope": [
        "source.json meta.structure.dictionary.json meta.structure.dictionary.value.json meta.structure.dictionary.json support.type.property-name.json"
      ],
      "settings": {
        "foreground": "#BD93F9"
      }
    },
    {
      "name": "JSON Key - Level 2",
      "scope": [
        "source.json meta.structure.dictionary.json meta.structure.dictionary.value.json meta.structure.dictionary.json meta.structure.dictionary.value.json meta.structure.dictionary.json support.type.property-name.json"
      ],
      "settings": {
        "foreground": "#BD93F9"
      }
    },
    {
      "name": "JSON Key - Level 3",
      "scope": [
        "source.json meta.structure.dictionary.json meta.structure.dictionary.value.json meta.structure.dictionary.json meta.structure.dictionary.value.json meta.structure.dictionary.json meta.structure.dictionary.value.json meta.structure.dictionary.json support.type.property-name.json"
      ],
      "settings": {
        "foreground": "#BD93F9"
      }
    },
    {
      "name": "JSON Key - Level 4",
      "scope": [
        "source.json meta.structure.dictionary.json meta.structure.dictionary.value.json meta.structure.dictionary.json meta.structure.dictionary.value.json meta.structure.dictionary.json meta.structure.dictionary.value.json meta.structure.dictionary.json meta.structure.dictionary.value.json meta.structure.dictionary.json support.type.property-name.json"
      ],
      "settings": {
        "foreground": "#BD93F9"
      }
    },
    {
      "name": "JSON Key - Level 5",
      "scope": [
        "source.json meta.structure.dictionary.json meta.structure.dictionary.value.json meta.structure.dictionary.json meta.structure.dictionary.value.json meta.structure.dictionary.json meta.structure.dictionary.value.json meta.structure.dictionary.json meta.structure.dictionary.value.json meta.structure.dictionary.json meta.structure.dictionary.value.json meta.structure.dictionary.json support.type.property-name.json"
      ],
      "settings": {
        "foreground": "#BD93F9"
      }
    },
    {
      "name": "JSON Key - Level 6",
      "scope": [
        "source.json meta.structure.dictionary.json meta.structure.dictionary.value.json meta.structure.dictionary.json meta.structure.dictionary.value.json meta.structure.dictionary.json meta.structure.dictionary.value.json meta.structure.dictionary.json meta.structure.dictionary.value.json meta.structure.dictionary.json meta.structure.dictionary.value.json meta.structure.dictionary.json support.type.property-name.json"
      ],
      "settings": {
        "foreground": "#BD93F9"
      }
    },
    {
      "name": "JSON Key - Level 7",
      "scope": [
        "source.json meta.structure.dictionary.json meta.structure.dictionary.value.json meta.structure.dictionary.json meta.structure.dictionary.value.json meta.structure.dictionary.json meta.structure.dictionary.value.json meta.structure.dictionary.json meta.structure.dictionary.value.json meta.structure.dictionary.json meta.structure.dictionary.value.json meta.structure.dictionary.json meta.structure.dictionary.value.json meta.structure.dictionary.json support.type.property-name.json"
      ],
      "settings": {
        "foreground": "#BD93F9"
      }
    },
    {
      "name": "JSON Key - Level 8",
      "scope": [
        "source.json meta.structure.dictionary.json meta.structure.dictionary.value.json meta.structure.dictionary.json meta.structure.dictionary.value.json meta.structure.dictionary.json meta.structure.dictionary.value.json meta.structure.dictionary.json meta.structure.dictionary.value.json meta.structure.dictionary.json meta.structure.dictionary.value.json meta.structure.dictionary.json meta.structure.dictionary.value.json meta.structure.dictionary.json support.type.property-name.json"
      ],
      "settings": {
        "foreground": "#BD93F9"
      }
    }
  ]
}